{
    "es": {
      "home": "All in one",
      "reservar": "Reserva simple",
      "reservar_largo": "Reservar a largo plazo",
      "misReservas": "Mis Reservas",
      "faq": "FAQ"
    },
    "it": {
        "home": "All in one",
        "reservar": "Prenotazione Simple",
        "reservar_largo": "Prenotazione Lungo Termine",
        "misReservas": "Miei Prenotazioni",
        "faq": "FAQ"
    },
    "en": {
        "home": "All in one",
        "reservar": "Simple Booking",
        "reservar_largo": "Long-term Booking",
        "misReservas": "My Bookings",
        "faq": "FAQ"
    }
  }